Workbook

Sheet Consignes
A1: Atelier — Courbes de croissance (skill financial-model-platinn-romandee)
A3: Objectif
A4: Préparer les hypothèses année 1 → année 5 d’une société de services suisse, au même format de drivers que la skill financial-model-platinn-romandee (prix, volume, capacité, marge & cash). Y1 et Y5 sont donnés ; vous (ou Claude) remplissez Y2–Y4.
A8: Déroulement
A9: 1. Feuille Courbes — compléter les cellules jaunes (Y2, Y3, Y4).
A10: 2. Interpolation linéaire par défaut ; une rupture est OK si vous la justifiez en commentaire.
A11: 3. Feuille Recap — vérifier que la capacité (FTE × heures × util.) suit la demande.
A12: 4. Envoyer le tableau à la skill platinn-romandee pour générer le plan Excel complet.
A13: 5. Ne pas ouvrir Corrige_formateur avant d’avoir tenté l’exercice.
A15: Cas
A16: Alpes Conseil Sàrl — conseil en organisation, Vaud, mode services (pas de SaaS, pas de VC). Devise CHF. Démarrage plan : janv. 2027. Fichier pédagogique — pas de conseil fiscal.
A19: Mapping skill (rappel)
A20: NewClients, ClientChurn, ProjectDemand, TargetUtil, RetainerFee/BillRate (via PriceIncrease), roles / FTE delivery → inputs JSON de financial-model-platinn-romandee (voir sample lemanconseil).

Sheet Courbes
A1: Alpes Conseil Sàrl — Courbes d’hypothèses (5 ans)
A2: Jaune = à compléter (Y2–Y4). Y1 et Y5 fournis. Aligné drivers skill financial-model-platinn-romandee (mode services).
A4: Clé skill | B4: Hypothèse | C4: Unité | D4: Y1 | E4: Y2 | F4: Y3 | G4: Y4 | H4: Y5
A5: RetainerFee | B5: 1. Prix — Honoraire retainer mensuel type | C5: CHF/mois | D5: 3800 | H5: 4500
A6: BillRate | B6: 1. Prix — Taux horaire projet | C6: CHF/h | D6: 175 | H6: 195
A7: PriceIncrease | B7: 1. Prix — Hausse prix annuelle (à partir de Y2) | C7: % | D7: — | H7: 0.03
A8: StartClients | B8: 2. Volume — Clients retainer en début de plan (fixe) | C8: nb | D8: 5 | H8: 5
A9: NewClients | B9: 2. Volume — Nouveaux clients retainer / mois | C9: nb/mois | D9: 0.5 | H9: 1.2
A10: ClientChurn | B10: 2. Volume — Churn clients / mois | C10: % | D10: 0.025 | H10: 0.018
A11: RetainerHours | B11: 2. Volume — Heures / client retainer / mois | C11: h | D11: 20 | H11: 22
A12: ProjectDemand | B12: 2. Volume — Demande projets (heures/mois) | C12: h/mois | D12: 120 | H12: 400
A13: DeliveryFTE | B13: 3. Capacité — FTE Delivery (moyenne année) | C13: FTE | D13: 3 | H13: 7
A14: HoursPerFTE | B14: 3. Capacité — Heures travaillées / FTE / mois | C14: h | D14: 150 | H14: 150
A15: TargetUtil | B15: 3. Capacité — Utilisation cible | C15: % | D15: 0.7 | H15: 0.76
A16: SubShare | B16: 3. Capacité — Part overflow en freelance | C16: % | D16: 0.4 | H16: 0.5
A17: SubCost | B17: 3. Capacité — Coût horaire freelance | C17: CHF/h | D17: 115 | H17: 130
A18: Rent | B18: 4. Cash — Loyer mensuel | C18: CHF/mois | D18: 3200 | H18: 5200
A19: DSO | B19: 4. Cash — Délai encaissement clients | C19: jours | D19: 45 | H19: 40
A20: MinCash | B20: 4. Cash — Plancher de trésorerie | C20: CHF | D20: 40000 | H20: 80000
A22: Indices
A23: Interpolation linéaire : valeur_Yn = Y1 + (Y5−Y1)×(n−1)/4. Pour PriceIncrease, Y1 n’existe pas (hausse dès Y2) : proposez une montée vers 3 %. StartClients reste constant (stock initial, pas une courbe).

Sheet Recap
A1: Recap capacité vs demande (après remplissage des Courbes)
A2: Quand Y2–Y4 sont remplis, ces indicateurs se calculent depuis Courbes. Capacité billable ≈ DeliveryFTE × HoursPerFTE × TargetUtil.
B3: Y1 | C3: Y2 | D3: Y3 | E3: Y4 | F3: Y5
A4: Indicateur | B4: Y1 | C4: Y2 | D4: Y3 | E4: Y4 | F4: Y5
A5: Nouveaux clients / mois | B5: =Courbes!D9 | C5: =Courbes!E9 | D5: =Courbes!F9 | E5: =Courbes!G9 | F5: =Courbes!H9
A6: Demande projets (h/mois) | B6: =Courbes!D12 | C6: =Courbes!E12 | D6: =Courbes!F12 | E6: =Courbes!G12 | F6: =Courbes!H12
A7: FTE Delivery | B7: =Courbes!D13 | C7: =Courbes!E13 | D7: =Courbes!F13 | E7: =Courbes!G13 | F7: =Courbes!H13
A8: Utilisation cible | B8: =Courbes!D15 | C8: =Courbes!E15 | D8: =Courbes!F15 | E8: =Courbes!G15 | F8: =Courbes!H15
A9: Capacité billable (h/mois) | B9: =Courbes!D13*Courbes!D14*Courbes!D15 | C9: =Courbes!E13*Courbes!E14*Courbes!E15 | D9: =Courbes!F13*Courbes!F14*Courbes!F15 | E9: =Courbes!G13*Courbes!G14*Courbes!G15 | F9: =Courbes!H13*Courbes!H14*Courbes!H15
A10: Demande totale approx. (projets + retainer start×h) | B10: =Courbes!D12+Courbes!D8*Courbes!D11 | C10: =Courbes!E12+Courbes!E8*Courbes!E11 | D10: =Courbes!F12+Courbes!F8*Courbes!F11 | E10: =Courbes!G12+Courbes!G8*Courbes!G11 | F10: =Courbes!H12+Courbes!H8*Courbes!H11
A12: Lecture
A13: Si Demande totale ≫ Capacité billable sur une année, il faut plus de FTE Delivery (ou moins de ProjectDemand / plus de freelances). C’est le cœur du driver 3 de la skill.
A16: * Approx. pédagogique : stock initial × heures ; la skill gère le stock de clients dynamiquement.

Sheet Prompt_skill
A1: Prompt type — enchaîner avec financial-model-platinn-romandee
A3: J’ai préparé les courbes 5 ans d’Alpes Conseil Sàrl (mode services, pas de subscriptions, pas de VC) dans growth-curve.xlsx, feuille Courbes. Utilise la skill financial-model-platinn-romandee : parte de ces hypothèses, pose-moi seulement les questions manquantes (équipe détaillée, canton, BFR, etc.), puis génère le JSON et le plan Excel.
A8: Variante sans la skill (Claude in Excel / Cursor)
A9: Sur la feuille Courbes, remplis Y2 Y3 Y4 par interpolation linéaire entre Y1 et Y5 (sauf StartClients constant et PriceIncrease dès Y2). Écris les formules Excel, pas des valeurs en dur si possible.

Sheet Corrige_formateur
A1: Corrigé indicatif — interpolation linéaire
A3: Formule
A4: Yn = Y1 + (Y5 − Y1) × (n − 1) / 4 pour n = 2,3,4
A6: Exemples
A7: NewClients : 0.5 → 0.675 → 0.85 → 1.025 → 1.2
A8: ProjectDemand : 120 → 190 → 260 → 330 → 400
A9: DeliveryFTE : 3.0 → 4.0 → 5.0 → 6.0 → 7.0
A10: TargetUtil : 70 % → 71.5 % → 73 % → 74.5 % → 76 %
A11: BillRate : 175 → 180 → 185 → 190 → 195
A12: PriceIncrease : — → 2.0 % → 2.5 % → 2.75 % → 3.0 % (exemple de montée)
A13: StartClients : 5 · 5 · 5 · 5 · 5
A14: HoursPerFTE : 150 constant
... A21: Ne montrez pas cette feuille avant la fin de l’exercice.
